setup.py
pk_common/__init__.py
pk_common_python.egg-info/PKG-INFO
pk_common_python.egg-info/SOURCES.txt
pk_common_python.egg-info/dependency_links.txt
pk_common_python.egg-info/requires.txt
pk_common_python.egg-info/top_level.txt