Metadata-Version: 1.0
Name: pk-common-python
Version: 0.2
Summary: Shared lib for Python server and client API for port knocking server "pk"
Home-page: https://github.com/anrosent/pk-common
Author: Anson Rosenthal
Author-email: anson.rosenthal@gmail.com
License: UNKNOWN
Platform: UNKNOWN
